kplaylisk/__init__.py
kplaylisk/main.py
kplaylisk/parsing.py
kplaylisk/process.py
kplaylisk-0.0.2.dist-info/LICENSE
kplaylisk-0.0.2.dist-info/METADATA
kplaylisk-0.0.2.dist-info/WHEEL
kplaylisk-0.0.2.dist-info/entry_points.txt
kplaylisk-0.0.2.dist-info/top_level.txt
kplaylisk-0.0.2.dist-info/RECORD
